[
    {
        "waves": [
            {
                "count": 8,
                "button": [
                    [0, 400],
                    [400, 0],
                    [400, 800],
                    [800, 400],
                    [0, -400],
                    [-400, 0],
                    [-400, -800],
                    [-800, -400]
                ]
            },
            {
                "count": 4,
                "morel": [
                    [0, 400],
                    [400, 0],
                    [400, 800],
                    [800, 400]
                ]
            },
            {
                "count": 4,
                "chanterelle": [
                    [0, 400],
                    [400, 0],
                    [400, 800],
                    [800, 400]
                ]
            },
            {
                "count": 8,
                "button": [
                    [0, 350],
                    [350, 0],
                    [350, 800],
                    [800, 350]
                ],
                "morel": [
                    [0, 400],
                    [400, 0],
                    [400, 800],
                    [800, 400]
                ]
            },
            {
                "count": 6,
                "morel": [
                    [0, 400],
                    [400, 0],
                    [400, 800],
                    [800, 400]
                ],
                "chanterelle": [
                    [800, 800],
                    [0, 0]
                ]

            },
            {
                "count": 12,
                "morel": [
                    [0, 400],
                    [400, 0]
                ],
                "chanterelle": [
                    [400, 800],
                    [800, 400]
                ],
                "button": [
                    [900, 400],
                    [1000, 400],
                    [1100, 400],
                    [1200, 400],
                    [1300, 400],
                    [1400, 400]
                ]

            }

        ],
        "relics": [
            {
                "type": "defense",
                "location": [400, 400]
            }
        ],
        "name": "The Plains",
        "description": "A cherished magic stump is under assault by hordes of mushrooms! Use every weapon at your disposal to eliminate them."
    },
    {
        "waves": [
            {
                "count": 1,
                "maitake": [
                    [400, 400]
                ],
                "button": [
                    [-200, 200],
                    [200, -200],
                    [600, 600]
                ]
            }
        ],
        "relics": [
            {
                "type": "defense",
                "location": [125, 125]
            },
            {
                "type": "defense",
                "location": [675, 675]
            },
            {
                "type": "defense",
                "location": [125, 675]
            },
            {
                "type": "defense",
                "location": [675, 125]
            }
        ],
        "name": "Maitake Madness",
        "description": "A giant maitake is threatening to destroy four of your precious gnome relics! Destroy it before it can cause any more damage. Stay alert, button mushrooms have been spotted nearby!"
    }
]